UploadHub/__init__.py
UploadHub/__main__.py
UploadHub/license.py
UploadHub/new.py
UploadHub/setup.py
UploadHub/upload.py
UploadHub/utils.py
UploadHub/data/config.json
UploadHub-0.0.7.dist-info/LICENSE
UploadHub-0.0.7.dist-info/METADATA
UploadHub-0.0.7.dist-info/WHEEL
UploadHub-0.0.7.dist-info/top_level.txt
UploadHub-0.0.7.dist-info/RECORD
