Metadata-Version: 2.1
Name: UploadHub
Version: 0.0.7
Summary: PYPI and GitHub package uploader.
Author: Armando Chaparro
Author-email: <pylejandria@gmail.com>
Keywords: python
Classifier: Development Status :: 1 - Planning
Classifier: Intended Audience :: Developers
Classifier: Programming Language :: Python :: 3
Classifier: Operating System :: Microsoft :: Windows
License-File: LICENSE
Requires-Dist: twine
Requires-Dist: ttkbootstrap
